ctg/ctgfuncts/__init__.py
ctg/ctgfuncts/ctg_cd.py
ctg/ctgfuncts/ctg_classes.py
ctg/ctgfuncts/ctg_effectif.py
ctg/ctgfuncts/ctg_plot.py
ctg/ctgfuncts/ctg_synthese.py
ctg/ctgfuncts/ctg_tools.py
ctg/ctgfuncts/CTG_RefFiles/CTG.yaml
ctg/ctgfuncts/CTG_RefFiles/CTG_correction.yaml
ctg/ctgfuncts/CTG_RefFiles/help.txt
ctg/ctgfuncts/CTG_RefFiles/help_config.txt
ctg/ctgfuncts/CTG_RefFiles/logo_ffvelo.ico
ctg/ctgfuncts/CTG_RefFiles/logoctg4.PNG
ctg/ctgfuncts/CTG_RefFiles/logoctg4.ico
ctg/ctgfuncts/CTG_RefFiles/memory_sorties.yml
ctg/ctgfuncts/CTG_RefFiles/memory_sorties_old.yml
ctg/ctgfuncts/CTG_RefFiles/villes_france_premium.csv
ctg/ctggui/__init__.py
ctg/ctggui/guiglobals.py
ctg/ctggui/guitools.py
ctg/ctggui/page_effectif.py
ctg/ctggui/pageclasses.py
ctg/ctggui/pagedivers.py
ctg/ctggui/pagesejour.py
ctg/ctggui/pagesorties.py
ctg/ctggui/pagesynthese.py
ctg/ctggui/pagetendance.py
ctg-1.1.0.dist-info/LICENSE
ctg-1.1.0.dist-info/METADATA
ctg-1.1.0.dist-info/WHEEL
ctg-1.1.0.dist-info/top_level.txt
ctg-1.1.0.dist-info/RECORD
