Metadata-Version: 2.1
Name: ctg
Version: 1.1.0
Summary: A toolbox for ctg statistics analysis
Home-page: https://github.com/Bertin-fap/ctgutils 
Author: f. bertin
Author-email: francois.bertin7@wanadoo.fr
License: MIT
Keywords: ffvelo,ctg
Platform: UNKNOWN
Classifier: Development Status :: 4 - Beta
Classifier: License :: OSI Approved :: MIT License
Classifier: Programming Language :: Python :: 3.9
Classifier: Topic :: Scientific/Engineering :: Information Analysis
Classifier: Operating System :: OS Independent
Classifier: Intended Audience :: Science/Research
License-File: LICENSE
Requires-Dist: openpyxl
Requires-Dist: pandas
Requires-Dist: plotly
Requires-Dist: folium
Requires-Dist: matplotlib
Requires-Dist: screeninfo
Requires-Dist: pyyaml
Requires-Dist: pandastable
